nkt/__init__.py
nkt/opt/__init__.py
nkt/opt/options.py
nkt/opt/parser.py
opt/__init__.py
opt/options.py
opt/parser.py
nkt-0.0.6.dist-info/LICENSE
nkt-0.0.6.dist-info/METADATA
nkt-0.0.6.dist-info/WHEEL
nkt-0.0.6.dist-info/top_level.txt
nkt-0.0.6.dist-info/RECORD
