Metadata-Version: 2.1
Name: nkt
Version: 0.0.6
Summary: NKT python packages
Author-email: Tuyen Nguyen <nktuyen@outlook.com>
Maintainer-email: Tuyen Nguyen <nktuyen@outlook.com>
License: GNU GENERAL PUBLIC LICENSE
Project-URL: Homepage, https://www.nktuyen.com/it/sw/packages/pynkt
Project-URL: Repository, https://github.com/nktuyen/pynkt.git
Keywords: optparser,option parser,option,tuyen,nkt,nktuyen,tuyen nguyen
Classifier: Programming Language :: Python
Requires-Python: >=3.8
License-File: LICENSE
